journal_scraper/__init__.py
journal_scraper/__main__.py
journal_scraper/api.py
journal_scraper/cache.py
journal_scraper/cli.py
journal_scraper/config.py
journal_scraper/epmc.py
journal_scraper/issn.py
journal_scraper/ncbi.py
journal_scraper/runner.py
journal_scraper/soup.py
journal_scraper/tellurium.py
journal_scraper/types.py
journal_scraper/utils.py
journal_scraper/xml_utils.py
journal_scraper-0.1.5.dist-info/METADATA
journal_scraper-0.1.5.dist-info/WHEEL
journal_scraper-0.1.5.dist-info/entry_points.txt
journal_scraper-0.1.5.dist-info/licenses/LICENSE
journal_scraper-0.1.5.dist-info/RECORD
