Metadata-Version: 2.4
Name: journal-scraper
Version: 0.1.5
Summary: Scraping Scientific Journal Articles
Author-email: arabidopsis <ian.castleden@uwa.edu.au>
License-File: LICENSE
Classifier: Development Status :: 4 - Beta
Classifier: Intended Audience :: Science/Research
Classifier: Programming Language :: Python :: 3 :: Only
Classifier: Topic :: Scientific/Engineering :: Bio-Informatics
Requires-Python: ~=3.11
Requires-Dist: beautifulsoup4<5,>=4.13.0
Requires-Dist: click<9,>=8.1.8
Requires-Dist: html-to-markdown<2,>=1.3.2
Requires-Dist: lxml<6,>=5.4.0
Requires-Dist: requests<3,>=2.32.3
Requires-Dist: tqdm<5,>=4.67.1
Provides-Extra: selenium
Requires-Dist: selenium-stealth<2,>=1.0.6; extra == 'selenium'
Requires-Dist: selenium<5,>=4.32.0; extra == 'selenium'
Requires-Dist: setuptools<81,>=80.8.0; extra == 'selenium'
Requires-Dist: undetected-chromedriver<4,>=3.5.5; extra == 'selenium'
